MANIFEST.in
README.md
requirements.txt
setup.py
demo/__init__.py
demo/generate_following.py
tests/__init__.py
tests/test_gen.py
tests/test_loader.py
tests/test_net.py
torch_gpt_2/__init__.py
torch_gpt_2/gen.py
torch_gpt_2/loader.py
torch_gpt_2/net.py
torch_gpt_2.egg-info/PKG-INFO
torch_gpt_2.egg-info/SOURCES.txt
torch_gpt_2.egg-info/dependency_links.txt
torch_gpt_2.egg-info/requires.txt
torch_gpt_2.egg-info/top_level.txt