Metadata-Version: 2.1
Name: torch-gpt-2
Version: 0.3.0
Summary: GPT-2 implemented in PyTorch
Home-page: https://github.com/CyberZHG/torch-gpt-2
Author: CyberZHG
Author-email: CyberZHG@gmail.com
License: MIT
Platform: UNKNOWN
Classifier: Programming Language :: Python :: 2.7
Classifier: Programming Language :: Python :: 3.6
Classifier: License :: OSI Approved :: MIT License
Classifier: Operating System :: OS Independent
